spikelink/__init__.py
spikelink/api.py
spikelink/adapters/__init__.py
spikelink/adapters/neo.py
spikelink/core/__init__.py
spikelink/core/codec.py
spikelink/core/packet.py
spikelink/hw/__init__.py
spikelink/stress/__init__.py
spikelink/stress/generators.py
spikelink/types/__init__.py
spikelink/types/spiketrain.py
spikelink/verification/__init__.py
spikelink/verification/degradation.py
spikelink/verification/suite.py
spikelink-0.1.1.dist-info/METADATA
spikelink-0.1.1.dist-info/WHEEL
spikelink-0.1.1.dist-info/licenses/LICENSE
spikelink-0.1.1.dist-info/RECORD
