Metadata-Version: 2.4
Name: spikelink
Version: 0.1.1
Summary: Spike-native transport for neuromorphic systems
Project-URL: Homepage, https://lightborneintelligence.com
Project-URL: Documentation, https://spikelink.readthedocs.io
Project-URL: Repository, https://github.com/lightborneintelligence/spikelink
Project-URL: Issues, https://github.com/lightborneintelligence/spikelink/issues
Author-email: Lightborne Intelligence <contact@lightborneintelligence.com>
License-Expression: Apache-2.0
License-File: LICENSE
Keywords: brainscales,ebrains,neo,neural,neuromorphic,spike-train,spiking,spinnaker
Classifier: Development Status :: 4 - Beta
Classifier: Intended Audience :: Science/Research
Classifier: License :: OSI Approved :: Apache Software License
Classifier: Operating System :: OS Independent
Classifier: Programming Language :: Python :: 3
Classifier: Programming Language :: Python :: 3.9
Classifier: Programming Language :: Python :: 3.10
Classifier: Programming Language :: Python :: 3.11
Classifier: Programming Language :: Python :: 3.12
Classifier: Topic :: Scientific/Engineering :: Artificial Intelligence
Classifier: Topic :: Scientific/Engineering :: Bio-Informatics
Requires-Python: >=3.9
Requires-Dist: numpy>=1.20.0
Provides-Extra: dev
Requires-Dist: black>=23.0.0; extra == 'dev'
Requires-Dist: mypy>=1.0.0; extra == 'dev'
Requires-Dist: pytest-cov>=4.0.0; extra == 'dev'
Requires-Dist: pytest>=7.0.0; extra == 'dev'
Requires-Dist: ruff>=0.1.0; extra == 'dev'
Provides-Extra: elephant
Requires-Dist: elephant>=0.12.0; extra == 'elephant'
Requires-Dist: neo>=0.12.0; extra == 'elephant'
Requires-Dist: quantities>=0.14.0; extra == 'elephant'
Provides-Extra: full
Requires-Dist: elephant>=0.12.0; extra == 'full'
Requires-Dist: neo>=0.12.0; extra == 'full'
Requires-Dist: quantities>=0.14.0; extra == 'full'
Provides-Extra: neo
Requires-Dist: neo>=0.12.0; extra == 'neo'
Requires-Dist: quantities>=0.14.0; extra == 'neo'
